{"_path":"/docs/team/services/perm/roles","_dir":"perm","_draft":false,"_partial":false,"_locale":"","title":"Roles","description":"Currently those role are defined :","body":{"type":"root","children":[{"type":"element","tag":"h1","props":{"id":"roles"},"children":[{"type":"text","value":"Roles"}]},{"type":"element","tag":"p","props":{},"children":[{"type":"text","value":"Currently those role are defined :"}]},{"type":"element","tag":"ul","props":{},"children":[{"type":"element","tag":"li","props":{},"children":[{"type":"text","value":"apidoc"}]},{"type":"element","tag":"li","props":{},"children":[{"type":"text","value":"browse_ref_obj"}]},{"type":"element","tag":"li","props":{},"children":[{"type":"text","value":"check"}]},{"type":"element","tag":"li","props":{},"children":[{"type":"text","value":"craft"}]},{"type":"element","tag":"li","props":{},"children":[{"type":"text","value":"credits"}]},{"type":"element","tag":"li","props":{},"children":[{"type":"text","value":"custom_domain"}]},{"type":"element","tag":"li","props":{},"children":[{"type":"text","value":"custom_style"}]},{"type":"element","tag":"li","props":{},"children":[{"type":"text","value":"sign"}]},{"type":"element","tag":"li","props":{},"children":[{"type":"text","value":"view"}]}]},{"type":"element","tag":"p","props":{},"children":[{"type":"text","value":"Roles are defined in the file "},{"type":"element","tag":"code","props":{"className":""},"children":[{"type":"text","value":"pp-ref-common/_sys/roles.yaml"}]},{"type":"text","value":"."}]},{"type":"element","tag":"p","props":{},"children":[{"type":"text","value":"This is an example of a role definition :"}]},{"type":"element","tag":"pre","props":{"className":"language-yaml shiki shiki-themes github-light github-dark","code":"# - -- --- -- - -- --- -- - -- --- -- - -- --- -- - -- --- -- - -- --- -- - --\n- id: browse_ref_obj\n  #TODO: split in many roles\n  desc: Accès à la liste des checklists/modules/craft\n  rules:\n    - GET {PROXY_CORE}/api/checklists\n    - GET {PROXY_CORE}/api/checklist/{ID}\n    - GET {PROXY_CORE}/api/checkmodules\n    - GET {PROXY_CORE}/api/checkmodule/{ID}\n    - GET {PROXY_CORE}/api/craftforms\n    - GET {PROXY_CORE}/api/craftform/{ID}\n    - GET {PROXY_CORE}/api/scenarios\n    - GET {PROXY_CORE}/api/scenario/{ID}\n    - GET {PROXY_CORE}/api/ref/info\n    - GET {PROXY_CORE}/api/ref/checklist/{ID}/static/{PATH}\n    - GET {PROXY_CORE}/api/ref/checkmodule/{ID}/static/{PATH}\n    - GET {PROXY_CORE}/api/ref/craftform/{ID}/static/{PATH}\n    - GET {PROXY_CORE}/api/ref/scenario/{ID}/static/{PATH}\n    - POST {PROXY_CORE}/api/ref/refresh\n    - POST {PROXY_CORE}/api/ref/sync\n# - -- --- -- - -- --- -- - -- --- -- - -- --- -- - -- --- -- - -- --- -- - --\n","language":"yaml","meta":"","style":""},"children":[{"type":"element","tag":"code","props":{"__ignoreMap":""},"children":[{"type":"element","tag":"span","props":{"class":"line","line":1},"children":[{"type":"element","tag":"span","props":{"style":"color:#6A737D;--shiki-dark:#6A737D"},"children":[{"type":"text","value":"# - -- --- -- - -- --- -- - -- --- -- - -- --- -- - -- --- -- - -- --- -- - --"}]}]},{"type":"element","tag":"span","props":{"class":"line","line":2},"children":[{"type":"element","tag":"span","props":{"style":"color:#24292E;--shiki-dark:#E1E4E8"},"children":[{"type":"text","value":"- "}]},{"type":"element","tag":"span","props":{"style":"color:#22863A;--shiki-dark:#85E89D"},"children":[{"type":"text","value":"id"}]},{"type":"element","tag":"span","props":{"style":"color:#24292E;--shiki-dark:#E1E4E8"},"children":[{"type":"text","value":": "}]},{"type":"element","tag":"span","props":{"style":"color:#032F62;--shiki-dark:#9ECBFF"},"children":[{"type":"text","value":"browse_ref_obj"}]}]},{"type":"element","tag":"span","props":{"class":"line","line":3},"children":[{"type":"element","tag":"span","props":{"style":"color:#6A737D;--shiki-dark:#6A737D"},"children":[{"type":"text","value":"  #TODO: split in many roles"}]}]},{"type":"element","tag":"span","props":{"class":"line","line":4},"children":[{"type":"element","tag":"span","props":{"style":"color:#22863A;--shiki-dark:#85E89D"},"children":[{"type":"text","value":"  desc"}]},{"type":"element","tag":"span","props":{"style":"color:#24292E;--shiki-dark:#E1E4E8"},"children":[{"type":"text","value":": "}]},{"type":"element","tag":"span","props":{"style":"color:#032F62;--shiki-dark:#9ECBFF"},"children":[{"type":"text","value":"Accès à la liste des checklists/modules/craft"}]}]},{"type":"element","tag":"span","props":{"class":"line","line":5},"children":[{"type":"element","tag":"span","props":{"style":"color:#22863A;--shiki-dark:#85E89D"},"children":[{"type":"text","value":"  rules"}]},{"type":"element","tag":"span","props":{"style":"color:#24292E;--shiki-dark:#E1E4E8"},"children":[{"type":"text","value":":"}]}]},{"type":"element","tag":"span","props":{"class":"line","line":6},"children":[{"type":"element","tag":"span","props":{"style":"color:#24292E;--shiki-dark:#E1E4E8"},"children":[{"type":"text","value":"    - "}]},{"type":"element","tag":"span","props":{"style":"color:#032F62;--shiki-dark:#9ECBFF"},"children":[{"type":"text","value":"GET {PROXY_CORE}/api/checklists"}]}]},{"type":"element","tag":"span","props":{"class":"line","line":7},"children":[{"type":"element","tag":"span","props":{"style":"color:#24292E;--shiki-dark:#E1E4E8"},"children":[{"type":"text","value":"    - "}]},{"type":"element","tag":"span","props":{"style":"color:#032F62;--shiki-dark:#9ECBFF"},"children":[{"type":"text","value":"GET {PROXY_CORE}/api/checklist/{ID}"}]}]},{"type":"element","tag":"span","props":{"class":"line","line":8},"children":[{"type":"element","tag":"span","props":{"style":"color:#24292E;--shiki-dark:#E1E4E8"},"children":[{"type":"text","value":"    - "}]},{"type":"element","tag":"span","props":{"style":"color:#032F62;--shiki-dark:#9ECBFF"},"children":[{"type":"text","value":"GET {PROXY_CORE}/api/checkmodules"}]}]},{"type":"element","tag":"span","props":{"class":"line","line":9},"children":[{"type":"element","tag":"span","props":{"style":"color:#24292E;--shiki-dark:#E1E4E8"},"children":[{"type":"text","value":"    - "}]},{"type":"element","tag":"span","props":{"style":"color:#032F62;--shiki-dark:#9ECBFF"},"children":[{"type":"text","value":"GET {PROXY_CORE}/api/checkmodule/{ID}"}]}]},{"type":"element","tag":"span","props":{"class":"line","line":10},"children":[{"type":"element","tag":"span","props":{"style":"color:#24292E;--shiki-dark:#E1E4E8"},"children":[{"type":"text","value":"    - "}]},{"type":"element","tag":"span","props":{"style":"color:#032F62;--shiki-dark:#9ECBFF"},"children":[{"type":"text","value":"GET {PROXY_CORE}/api/craftforms"}]}]},{"type":"element","tag":"span","props":{"class":"line","line":11},"children":[{"type":"element","tag":"span","props":{"style":"color:#24292E;--shiki-dark:#E1E4E8"},"children":[{"type":"text","value":"    - "}]},{"type":"element","tag":"span","props":{"style":"color:#032F62;--shiki-dark:#9ECBFF"},"children":[{"type":"text","value":"GET {PROXY_CORE}/api/craftform/{ID}"}]}]},{"type":"element","tag":"span","props":{"class":"line","line":12},"children":[{"type":"element","tag":"span","props":{"style":"color:#24292E;--shiki-dark:#E1E4E8"},"children":[{"type":"text","value":"    - "}]},{"type":"element","tag":"span","props":{"style":"color:#032F62;--shiki-dark:#9ECBFF"},"children":[{"type":"text","value":"GET {PROXY_CORE}/api/scenarios"}]}]},{"type":"element","tag":"span","props":{"class":"line","line":13},"children":[{"type":"element","tag":"span","props":{"style":"color:#24292E;--shiki-dark:#E1E4E8"},"children":[{"type":"text","value":"    - "}]},{"type":"element","tag":"span","props":{"style":"color:#032F62;--shiki-dark:#9ECBFF"},"children":[{"type":"text","value":"GET {PROXY_CORE}/api/scenario/{ID}"}]}]},{"type":"element","tag":"span","props":{"class":"line","line":14},"children":[{"type":"element","tag":"span","props":{"style":"color:#24292E;--shiki-dark:#E1E4E8"},"children":[{"type":"text","value":"    - "}]},{"type":"element","tag":"span","props":{"style":"color:#032F62;--shiki-dark:#9ECBFF"},"children":[{"type":"text","value":"GET {PROXY_CORE}/api/ref/info"}]}]},{"type":"element","tag":"span","props":{"class":"line","line":15},"children":[{"type":"element","tag":"span","props":{"style":"color:#24292E;--shiki-dark:#E1E4E8"},"children":[{"type":"text","value":"    - "}]},{"type":"element","tag":"span","props":{"style":"color:#032F62;--shiki-dark:#9ECBFF"},"children":[{"type":"text","value":"GET {PROXY_CORE}/api/ref/checklist/{ID}/static/{PATH}"}]}]},{"type":"element","tag":"span","props":{"class":"line","line":16},"children":[{"type":"element","tag":"span","props":{"style":"color:#24292E;--shiki-dark:#E1E4E8"},"children":[{"type":"text","value":"    - "}]},{"type":"element","tag":"span","props":{"style":"color:#032F62;--shiki-dark:#9ECBFF"},"children":[{"type":"text","value":"GET {PROXY_CORE}/api/ref/checkmodule/{ID}/static/{PATH}"}]}]},{"type":"element","tag":"span","props":{"class":"line","line":17},"children":[{"type":"element","tag":"span","props":{"style":"color:#24292E;--shiki-dark:#E1E4E8"},"children":[{"type":"text","value":"    - "}]},{"type":"element","tag":"span","props":{"style":"color:#032F62;--shiki-dark:#9ECBFF"},"children":[{"type":"text","value":"GET {PROXY_CORE}/api/ref/craftform/{ID}/static/{PATH}"}]}]},{"type":"element","tag":"span","props":{"class":"line","line":18},"children":[{"type":"element","tag":"span","props":{"style":"color:#24292E;--shiki-dark:#E1E4E8"},"children":[{"type":"text","value":"    - "}]},{"type":"element","tag":"span","props":{"style":"color:#032F62;--shiki-dark:#9ECBFF"},"children":[{"type":"text","value":"GET {PROXY_CORE}/api/ref/scenario/{ID}/static/{PATH}"}]}]},{"type":"element","tag":"span","props":{"class":"line","line":19},"children":[{"type":"element","tag":"span","props":{"style":"color:#24292E;--shiki-dark:#E1E4E8"},"children":[{"type":"text","value":"    - "}]},{"type":"element","tag":"span","props":{"style":"color:#032F62;--shiki-dark:#9ECBFF"},"children":[{"type":"text","value":"POST {PROXY_CORE}/api/ref/refresh"}]}]},{"type":"element","tag":"span","props":{"class":"line","line":20},"children":[{"type":"element","tag":"span","props":{"style":"color:#24292E;--shiki-dark:#E1E4E8"},"children":[{"type":"text","value":"    - "}]},{"type":"element","tag":"span","props":{"style":"color:#032F62;--shiki-dark:#9ECBFF"},"children":[{"type":"text","value":"POST {PROXY_CORE}/api/ref/sync"}]}]},{"type":"element","tag":"span","props":{"class":"line","line":21},"children":[{"type":"element","tag":"span","props":{"style":"color:#6A737D;--shiki-dark:#6A737D"},"children":[{"type":"text","value":"# - -- --- -- - -- --- -- - -- --- -- - -- --- -- - -- --- -- - -- --- -- - --"}]}]}]}]},{"type":"element","tag":"style","props":{},"children":[{"type":"text","value":"html.dark .shiki span {color: var(--shiki-dark) !important;background: var(--shiki-dark-bg) !important;font-style: var(--shiki-dark-font-style) !important;font-weight: var(--shiki-dark-font-weight) !important;text-decoration: var(--shiki-dark-text-decoration) !important;}"}]}],"toc":{"title":"","searchDepth":2,"depth":2,"links":[]}},"_type":"markdown","_id":"content:10.docs:80.team:10.services:perm:roles.md","_source":"content","_file":"10.docs/80.team/10.services/perm/roles.md","_extension":"md"}