{"_path":"/docs/front/pages/pricing","_dir":"pages","_draft":false,"_partial":false,"_locale":"","title":"/pricing","description":"Pricing page at /pricing","body":{"type":"root","children":[{"type":"element","tag":"h1","props":{"id":"pricing"},"children":[{"type":"text","value":"/pricing"}]},{"type":"element","tag":"p","props":{},"children":[{"type":"text","value":"Pricing page at "},{"type":"element","tag":"a","props":{"href":"/pricing"},"children":[{"type":"text","value":"/pricing"}]}]},{"type":"element","tag":"p","props":{},"children":[{"type":"text","value":"Pricing values are at "},{"type":"element","tag":"a","props":{"href":"/data/pricing.json"},"children":[{"type":"text","value":"/data/pricing.json"}]},{"type":"text","value":"."}]}],"toc":{"title":"","searchDepth":2,"depth":2,"links":[]}},"_type":"markdown","_id":"content:10.docs:10.front:pages:pricing.md","_source":"content","_file":"10.docs/10.front/pages/pricing.md","_extension":"md"}