{"_path":"/docs/craftform/simple","_dir":"craftform","_draft":false,"_partial":false,"_locale":"","title":"Simple","description":"A simple craftform","body":{"type":"root","children":[{"type":"element","tag":"h1","props":{"id":"simple"},"children":[{"type":"text","value":"Simple"}]},{"type":"element","tag":"p","props":{},"children":[{"type":"text","value":"A simple craftform"}]},{"type":"element","tag":"h2","props":{"id":"folder-my_craftform"},"children":[{"type":"text","value":"Folder my_craftform"}]},{"type":"element","tag":"p","props":{},"children":[{"type":"text","value":"Create an empty folder "},{"type":"element","tag":"code","props":{"className":""},"children":[{"type":"text","value":"my_craftform"}]},{"type":"text","value":" where to put all the files."}]},{"type":"element","tag":"h2","props":{"id":"file-basecraftformyaml"},"children":[{"type":"text","value":"File base.craftform.yaml"}]},{"type":"element","tag":"p","props":{},"children":[{"type":"text","value":"Create a "},{"type":"element","tag":"code","props":{"className":""},"children":[{"type":"text","value":"base.craftform.yaml"}]},{"type":"text","value":" with this content :"}]},{"type":"element","tag":"pre","props":{"className":"language-yaml shiki shiki-themes github-light github-dark","code":"# yaml-language-server: $schema=https://paxpar.gitlab.io/schemas/craftform-1.0.schema.json\n$schema: https://paxpar.tech/schema/craft/1\nname: Mon Ordre d'intervention\nversion: \"1\"\ndesc: Créer un ordre d'intervention avec les carnets d'habilitations des intervenants\n","language":"yaml","meta":"","style":""},"children":[{"type":"element","tag":"code","props":{"__ignoreMap":""},"children":[{"type":"element","tag":"span","props":{"class":"line","line":1},"children":[{"type":"element","tag":"span","props":{"style":"color:#6A737D;--shiki-dark:#6A737D"},"children":[{"type":"text","value":"# yaml-language-server: $schema=https://paxpar.gitlab.io/schemas/craftform-1.0.schema.json"}]}]},{"type":"element","tag":"span","props":{"class":"line","line":2},"children":[{"type":"element","tag":"span","props":{"style":"color:#22863A;--shiki-dark:#85E89D"},"children":[{"type":"text","value":"$schema"}]},{"type":"element","tag":"span","props":{"style":"color:#24292E;--shiki-dark:#E1E4E8"},"children":[{"type":"text","value":": "}]},{"type":"element","tag":"span","props":{"style":"color:#032F62;--shiki-dark:#9ECBFF"},"children":[{"type":"text","value":"https://paxpar.tech/schema/craft/1"}]}]},{"type":"element","tag":"span","props":{"class":"line","line":3},"children":[{"type":"element","tag":"span","props":{"style":"color:#22863A;--shiki-dark:#85E89D"},"children":[{"type":"text","value":"name"}]},{"type":"element","tag":"span","props":{"style":"color:#24292E;--shiki-dark:#E1E4E8"},"children":[{"type":"text","value":": "}]},{"type":"element","tag":"span","props":{"style":"color:#032F62;--shiki-dark:#9ECBFF"},"children":[{"type":"text","value":"Mon Ordre d'intervention"}]}]},{"type":"element","tag":"span","props":{"class":"line","line":4},"children":[{"type":"element","tag":"span","props":{"style":"color:#22863A;--shiki-dark:#85E89D"},"children":[{"type":"text","value":"version"}]},{"type":"element","tag":"span","props":{"style":"color:#24292E;--shiki-dark:#E1E4E8"},"children":[{"type":"text","value":": "}]},{"type":"element","tag":"span","props":{"style":"color:#032F62;--shiki-dark:#9ECBFF"},"children":[{"type":"text","value":"\"1\""}]}]},{"type":"element","tag":"span","props":{"class":"line","line":5},"children":[{"type":"element","tag":"span","props":{"style":"color:#22863A;--shiki-dark:#85E89D"},"children":[{"type":"text","value":"desc"}]},{"type":"element","tag":"span","props":{"style":"color:#24292E;--shiki-dark:#E1E4E8"},"children":[{"type":"text","value":": "}]},{"type":"element","tag":"span","props":{"style":"color:#032F62;--shiki-dark:#9ECBFF"},"children":[{"type":"text","value":"Créer un ordre d'intervention avec les carnets d'habilitations des intervenants"}]}]}]}]},{"type":"element","tag":"h2","props":{"id":"file-schemayaml"},"children":[{"type":"text","value":"File schema.yaml"}]},{"type":"element","tag":"p","props":{},"children":[{"type":"text","value":"Create a "},{"type":"element","tag":"code","props":{"className":""},"children":[{"type":"text","value":"schema.yaml"}]},{"type":"text","value":" with this content :"}]},{"type":"element","tag":"pre","props":{"className":"language-yaml shiki shiki-themes github-light github-dark","code":"title: Ordre d'intervention\ntype: object\nproperties:\n  adresse:\n    type: string\n  cp:\n    type: string\n","language":"yaml","meta":"","style":""},"children":[{"type":"element","tag":"code","props":{"__ignoreMap":""},"children":[{"type":"element","tag":"span","props":{"class":"line","line":1},"children":[{"type":"element","tag":"span","props":{"style":"color:#22863A;--shiki-dark:#85E89D"},"children":[{"type":"text","value":"title"}]},{"type":"element","tag":"span","props":{"style":"color:#24292E;--shiki-dark:#E1E4E8"},"children":[{"type":"text","value":": "}]},{"type":"element","tag":"span","props":{"style":"color:#032F62;--shiki-dark:#9ECBFF"},"children":[{"type":"text","value":"Ordre d'intervention"}]}]},{"type":"element","tag":"span","props":{"class":"line","line":2},"children":[{"type":"element","tag":"span","props":{"style":"color:#22863A;--shiki-dark:#85E89D"},"children":[{"type":"text","value":"type"}]},{"type":"element","tag":"span","props":{"style":"color:#24292E;--shiki-dark:#E1E4E8"},"children":[{"type":"text","value":": "}]},{"type":"element","tag":"span","props":{"style":"color:#032F62;--shiki-dark:#9ECBFF"},"children":[{"type":"text","value":"object"}]}]},{"type":"element","tag":"span","props":{"class":"line","line":3},"children":[{"type":"element","tag":"span","props":{"style":"color:#22863A;--shiki-dark:#85E89D"},"children":[{"type":"text","value":"properties"}]},{"type":"element","tag":"span","props":{"style":"color:#24292E;--shiki-dark:#E1E4E8"},"children":[{"type":"text","value":":"}]}]},{"type":"element","tag":"span","props":{"class":"line","line":4},"children":[{"type":"element","tag":"span","props":{"style":"color:#22863A;--shiki-dark:#85E89D"},"children":[{"type":"text","value":"  adresse"}]},{"type":"element","tag":"span","props":{"style":"color:#24292E;--shiki-dark:#E1E4E8"},"children":[{"type":"text","value":":"}]}]},{"type":"element","tag":"span","props":{"class":"line","line":5},"children":[{"type":"element","tag":"span","props":{"style":"color:#22863A;--shiki-dark:#85E89D"},"children":[{"type":"text","value":"    type"}]},{"type":"element","tag":"span","props":{"style":"color:#24292E;--shiki-dark:#E1E4E8"},"children":[{"type":"text","value":": "}]},{"type":"element","tag":"span","props":{"style":"color:#032F62;--shiki-dark:#9ECBFF"},"children":[{"type":"text","value":"string"}]}]},{"type":"element","tag":"span","props":{"class":"line","line":6},"children":[{"type":"element","tag":"span","props":{"style":"color:#22863A;--shiki-dark:#85E89D"},"children":[{"type":"text","value":"  cp"}]},{"type":"element","tag":"span","props":{"style":"color:#24292E;--shiki-dark:#E1E4E8"},"children":[{"type":"text","value":":"}]}]},{"type":"element","tag":"span","props":{"class":"line","line":7},"children":[{"type":"element","tag":"span","props":{"style":"color:#22863A;--shiki-dark:#85E89D"},"children":[{"type":"text","value":"    type"}]},{"type":"element","tag":"span","props":{"style":"color:#24292E;--shiki-dark:#E1E4E8"},"children":[{"type":"text","value":": "}]},{"type":"element","tag":"span","props":{"style":"color:#032F62;--shiki-dark:#9ECBFF"},"children":[{"type":"text","value":"string"}]}]}]}]},{"type":"element","tag":"h2","props":{"id":"preview"},"children":[{"type":"text","value":"Preview"}]},{"type":"element","tag":"p","props":{},"children":[{"type":"text","value":"You can already see your working craftform."}]},{"type":"element","tag":"h2","props":{"id":"embeded-preview"},"children":[{"type":"text","value":"Embeded preview"}]},{"type":"element","tag":"ppw-wizard-craft","props":{"craft_id":"frozen.paf.paf.craftform"},"children":[{"type":"element","tag":"style","props":{},"children":[{"type":"text","value":"html.dark .shiki span {color: var(--shiki-dark) !important;background: var(--shiki-dark-bg) !important;font-style: var(--shiki-dark-font-style) !important;font-weight: var(--shiki-dark-font-weight) !important;text-decoration: var(--shiki-dark-text-decoration) !important;}"}]}]}],"toc":{"title":"","searchDepth":2,"depth":2,"links":[{"id":"folder-my_craftform","depth":2,"text":"Folder my_craftform"},{"id":"file-basecraftformyaml","depth":2,"text":"File base.craftform.yaml"},{"id":"file-schemayaml","depth":2,"text":"File schema.yaml"},{"id":"preview","depth":2,"text":"Preview"},{"id":"embeded-preview","depth":2,"text":"Embeded preview"}]}},"_type":"markdown","_id":"content:10.docs:30.craftform:0.simple.md","_source":"content","_file":"10.docs/30.craftform/0.simple.md","_extension":"md"}