{"_path":"/paxpar/alert","_dir":"paxpar","_draft":false,"_partial":false,"_locale":"","title":"Alert","description":"our alert component:","body":{"type":"root","children":[{"type":"element","tag":"h1","props":{"id":"alert"},"children":[{"type":"text","value":"Alert"}]},{"type":"element","tag":"p","props":{},"children":[{"type":"text","value":"our alert component:"}]},{"type":"element","tag":"ppw-alert","props":{"msg":"Lorem Ipsum"},"children":[]},{"type":"element","tag":"p","props":{},"children":[{"type":"text","value":"standard alert component:"}]},{"type":"element","tag":"alert","props":{"type":"info"},"children":[{"type":"element","tag":"p","props":{},"children":[{"type":"text","value":"Check out an "},{"type":"element","tag":"strong","props":{},"children":[{"type":"text","value":"info"}]},{"type":"text","value":" alert with "},{"type":"element","tag":"code","props":{"className":""},"children":[{"type":"text","value":"code"}]},{"type":"text","value":" and a "},{"type":"element","tag":"a","props":{"href":"/"},"children":[{"type":"text","value":"link"}]},{"type":"text","value":"."}]}]}],"toc":{"title":"","searchDepth":2,"depth":2,"links":[]}},"_type":"markdown","_id":"content:3.paxpar:alert.md","_source":"content","_file":"3.paxpar/alert.md","_extension":"md"}