{"_path":"/docs/team/services/auth/namespace","_dir":"auth","_draft":false,"_partial":false,"_locale":"","title":"Namespaces","description":"!!! new \"Not implemented yet\"","body":{"type":"root","children":[{"type":"element","tag":"h1","props":{"id":"namespaces"},"children":[{"type":"text","value":"Namespaces"}]},{"type":"element","tag":"p","props":{},"children":[{"type":"text","value":"!!! new \"Not implemented yet\""}]},{"type":"element","tag":"p","props":{},"children":[{"type":"text","value":"paxpar assets (checklist, craft, modules, ...)\ncan be places in namespaces."}]},{"type":"element","tag":"p","props":{},"children":[{"type":"text","value":"Namespaces are private.\nThey use the usual dot notation."}]},{"type":"element","tag":"p","props":{},"children":[{"type":"text","value":"Valid namespaces :"}]},{"type":"element","tag":"ul","props":{},"children":[{"type":"element","tag":"li","props":{},"children":[{"type":"text","value":"cdc"}]},{"type":"element","tag":"li","props":{},"children":[{"type":"text","value":"qa.cdc"}]},{"type":"element","tag":"li","props":{},"children":[{"type":"text","value":"prod.cdc"}]}]},{"type":"element","tag":"h2","props":{"id":"backend"},"children":[{"type":"text","value":"backend"}]},{"type":"element","tag":"p","props":{},"children":[{"type":"text","value":"Namespaces supported backends are :"}]},{"type":"element","tag":"ul","props":{},"children":[{"type":"element","tag":"li","props":{},"children":[{"type":"text","value":"local filesystem"}]},{"type":"element","tag":"li","props":{},"children":[{"type":"text","value":"S3 bucket (with or without subpath)"}]},{"type":"element","tag":"li","props":{},"children":[{"type":"text","value":"gitlab project (with or without subpath)"}]},{"type":"element","tag":"li","props":{},"children":[{"type":"text","value":"github project (with or without subpath)"}]}]},{"type":"element","tag":"h2","props":{"id":"folder-structure"},"children":[{"type":"text","value":"folder structure"}]},{"type":"element","tag":"pre","props":{"code":"root\n|__checklist\n|__craft\n|__module\n"},"children":[{"type":"element","tag":"code","props":{"__ignoreMap":""},"children":[{"type":"text","value":"root\n|__checklist\n|__craft\n|__module\n"}]}]}],"toc":{"title":"","searchDepth":2,"depth":2,"links":[{"id":"backend","depth":2,"text":"backend"},{"id":"folder-structure","depth":2,"text":"folder structure"}]}},"_type":"markdown","_id":"content:10.docs:80.team:10.services:auth:namespace.md","_source":"content","_file":"10.docs/80.team/10.services/auth/namespace.md","_extension":"md"}